LICENSE
README.md
setup.py
api_manager/__init__.py
api_manager/constants.py
api_manager/exceptions.py
api_manager/headers.py
api_manager/logger.py
api_manager/methods.py
api_manager/settings.py
api_manager/token.py
api_manager/utils.py
api_manager.egg-info/PKG-INFO
api_manager.egg-info/SOURCES.txt
api_manager.egg-info/dependency_links.txt
api_manager.egg-info/requires.txt
api_manager.egg-info/top_level.txt
api_manager/async_response/__init__.py
api_manager/async_response/lazy_request.py
api_manager/async_response/utils.py
api_manager/templates/log_template.html