Metadata-Version: 2.1
Name: api-manager
Version: 0.2.5
Summary: Api Manager
Home-page: https://gitlab.alemira.dev/platform/qa/api-manager
Author: Nikita Filonov
Author-email: nf@alemira.com
License-File: LICENSE
